timer.v
// Timer module
module Timer (
input clk,
input reset,
input enable,
output reg trigger
);
reg [31:0] count;

always @(posedge clk) begin
if (reset) begin
count <= 0;
trigger <= 0;
end else begin
if (enable) begin
count <= count + 1;
if (count == 1000000) begin
trigger <= 1;
count <= 0;
end
end else begin
trigger <= 0;
count <= 0;
end
end
end
endmodule

uart.v
// UART module
module UART (
  input clk,
  input reset,
  input [7:0] data_in,
  input tx_enable,
  output reg [7:0] data_out,
  output reg tx_busy
);
  reg [7:0] tx_reg;
  reg tx_empty, tx_shift_reg;

  always @(posedge clk) begin
    if (reset) begin
      tx_empty <= 1;
      tx_shift_reg <= 0;
      tx_reg <= 0;
    end else begin
      if (tx_enable) begin
        if (tx_empty) begin
          tx_reg <= data_in;
          tx_shift_reg <= 1;
          tx_empty <= 0;
        end
      end else begin
        if (!tx_empty) begin
          tx_shift_reg <= 1;
        end
      end
    end
  end

  always @(posedge clk) begin
    if (tx_shift_reg) begin
      if (tx_busy) begin
        tx_shift_reg <= 0;
        tx_empty <= 1;
      end else begin
        data_out <= tx_reg;
        tx_busy <= 1;
        tx_shift_reg <= 0;
      end
    end else begin
      data_out <= 0;
    end
  end
endmodule

memory.v
// Memory module
module Memory (
  input [31:0] address,
  input [31:0] data_in,
  input write_enable,
  output reg [31:0] data_out
);
  reg [31:0] memory [0:1023];

  always @(*) begin
    if (write_enable) begin
      memory[address] <= data_in;
    end
    data_out <= memory[address];
  end
endmodule

cpu.v
// CPU module
module CPU (
  input [31:0] input1,
  input [31:0] input2,
  input [3:0] operation,
  output reg [31:0] result
);
  always @(*) begin
    case (operation)
      4'b0000: result <= input1 + input2; // Addition
      4'b0001: result <= input1 - input2; // Subtraction
      4'b0010: result <= input1 & input2; // Bitwise AND
      4'b0011: result <= input1 | input2; // Bitwise OR
      4'b0100: result <= input1 ^ input2; // Bitwise XOR
      default: result <= 0; // Default to 0
    endcase
  end
endmodule

top.v
// Top-level module
module Top (
input clk,
input reset,
input [31:0] cpu_input1,
input [31:0] cpu_input2,
input [3:0] cpu_operation,
input [31:0] memory_address,
input [31:0] memory_data_in,
input memory_write_enable,
input [7:0] uart_data_in,
input uart_tx_enable,
input timer_enable,
output [31:0] cpu_result,
output [31:0] memory_data_out,
output [7:0] uart_data_out,
output uart_tx_busy,
output timer_trigger,
output reg zero_flag
);
CPU cpu_inst (
.input1(cpu_input1),
.input2(cpu_input2),
.operation(cpu_operation),
.result(cpu_result)
);

Memory memory_inst (
.address(memory_address),
.data_in(memory_data_in),
.write_enable(memory_write_enable),
.data_out(memory_data_out)
);


UART uart_inst (
.clk(clk),
.reset(reset),
.data_in(uart_data_in),
.tx_enable(uart_tx_enable),
.data_out(uart_data_out),
.tx_busy(uart_tx_busy)
);

Timer timer_inst (
.clk(clk),
.reset(reset),
.enable(timer_enable),
.trigger(timer_trigger)
);
endmodule

testbench.v
// Testbench module
module Testbench ();
reg clk, reset;
reg [31:0] cpu_input1, cpu_input2, memory_address, memory_data_in;
reg [3:0] cpu_operation;
reg memory_write_enable, uart_tx_enable, timer_enable;
reg [7:0] uart_data_in;
wire [31:0] cpu_result, memory_data_out;
wire [7:0] uart_data_out;
wire uart_tx_busy, timer_trigger;
wire zero_flag;

Top top_inst (
.clk(clk),
.reset(reset),
.cpu_input1(cpu_input1),
.cpu_input2(cpu_input2),
.cpu_operation(cpu_operation),
.memory_address(memory_address),
.memory_data_in(memory_data_in),
.memory_write_enable(memory_write_enable),
.uart_data_in(uart_data_in),
.uart_tx_enable(uart_tx_enable),
.timer_enable(timer_enable),
.cpu_result(cpu_result),
.memory_data_out(memory_data_out),
.uart_data_out(uart_data_out),
.uart_tx_busy(uart_tx_busy),
.timer_trigger(timer_trigger),
.zero_flag(zero_flag)
);
integer i;
initial begin
    
    for(i=0;i<20;i=i+1) begin
clk = 0+ 10*i;
reset = 1;
cpu_input1 = 2*i;
cpu_input2 = 0 + 3*i;
cpu_operation = i%5;
memory_address = i;
memory_data_in = 30*i;
memory_write_enable = i%2;
uart_data_in = 15*i;
uart_tx_enable = i%2;
timer_enable = i%2;
#10 reset = 0;
    end

#100000;

$finish;
end

always #5 clk = ~clk;
initial begin
        $dumpfile("output.vcd");
        $dumpvars(1);
    end
endmodule

output.vcd
$date
	Fri May 05 23:41:59 2023
$end
$version
	Icarus Verilog
$end
$timescale
	1s
$end
$scope module Testbench $end
$var wire 1 ! zero_flag $end
$var wire 1 " uart_tx_busy $end
$var wire 8 # uart_data_out [7:0] $end
$var wire 1 $ timer_trigger $end
$var wire 32 % memory_data_out [31:0] $end
$var wire 32 & cpu_result [31:0] $end
$var reg 1 ' clk $end
$var reg 32 ( cpu_input1 [31:0] $end
$var reg 32 ) cpu_input2 [31:0] $end
$var reg 4 * cpu_operation [3:0] $end
$var reg 32 + memory_address [31:0] $end
$var reg 32 , memory_data_in [31:0] $end
$var reg 1 - memory_write_enable $end
$var reg 1 . reset $end
$var reg 1 / timer_enable $end
$var reg 8 0 uart_data_in [7:0] $end
$var reg 1 1 uart_tx_enable $end
$var integer 32 2 i [31:0] $end
$upscope $end
$enddefinitions $end
$comment Show the parameter values. $end
$dumpall
$end
#0
$dumpvars
b0 2
01
b0 0
0/
1.
0-
b0 ,
b0 +
b0 *
b0 )
b0 (
0'
b0 &
bx %
x$
bx #
x"
x!
$end
#5
b0 #
0$
1'
#10
b11110 %
b11111111111111111111111111111111 &
1/
11
b1111 0
1-
b11110 ,
b1 +
b1 *
b11 )
b10 (
1'
b1 2
1.
#15
0'
#20
bx %
b100 &
1'
0/
01
b11110 0
0-
b111100 ,
b10 +
b10 *
b110 )
b100 (
b10 2
1.
#25
0'
#30
b1011010 %
b1111 &
1'
1/
11
b101101 0
1-
b1011010 ,
b11 +
b11 *
b1001 )
b110 (
b11 2
1.
#35
0'
#40
bx %
b100 &
1'
0/
01
b111100 0
0-
b1111000 ,
b100 +
b100 *
b1100 )
b1000 (
b100 2
1.
#45
0'
#50
b10010110 %
b11001 &
1'
1/
11
b1001011 0
1-
b10010110 ,
b101 +
b0 *
b1111 )
b1010 (
b101 2
1.
#55
0'
#60
bx %
b11111111111111111111111111111010 &
1'
0/
01
b1011010 0
0-
b10110100 ,
b110 +
b1 *
b10010 )
b1100 (
b110 2
1.
#65
0'
#70
b11010010 %
b100 &
1'
1/
11
b1101001 0
1-
b11010010 ,
b111 +
b10 *
b10101 )
b1110 (
b111 2
1.
#75
0'
#80
bx %
b11000 &
1'
0/
01
b1111000 0
0-
b11110000 ,
b1000 +
b11 *
b11000 )
b10000 (
b1000 2
1.
#85
0'
#90
b100001110 %
b1001 &
1'
1/
11
b10000111 0
1-
b100001110 ,
b1001 +
b100 *
b11011 )
b10010 (
b1001 2
1.
#95
0'
#100
bx %
b110010 &
1'
0/
01
b10010110 0
0-
b100101100 ,
b1010 +
b0 *
b11110 )
b10100 (
b1010 2
1.
#105
0'
#110
b101001010 %
b11111111111111111111111111110101 &
1'
1/
11
b10100101 0
1-
b101001010 ,
b1011 +
b1 *
b100001 )
b10110 (
b1011 2
1.
#115
0'
#120
bx %
b0 &
1'
0/
01
b10110100 0
0-
b101101000 ,
b1100 +
b10 *
b100100 )
b11000 (
b1100 2
1.
#125
0'
#130
b110000110 %
b111111 &
1'
1/
11
b11000011 0
1-
b110000110 ,
b1101 +
b11 *
b100111 )
b11010 (
b1101 2
1.
#135
0'
#140
bx %
b110110 &
1'
0/
01
b11010010 0
0-
b110100100 ,
b1110 +
b100 *
b101010 )
b11100 (
b1110 2
1.
#145
0'
#150
b111000010 %
b1001011 &
1'
1/
11
b11100001 0
1-
b111000010 ,
b1111 +
b0 *
b101101 )
b11110 (
b1111 2
1.
#155
0'
#160
bx %
b11111111111111111111111111110000 &
1'
0/
01
b11110000 0
0-
b111100000 ,
b10000 +
b1 *
b110000 )
b100000 (
b10000 2
1.
#165
0'
#170
b111111110 %
b100010 &
1'
1/
11
b11111111 0
1-
b111111110 ,
b10001 +
b10 *
b110011 )
b100010 (
b10001 2
1.
#175
0'
#180
bx %
b110110 &
1'
0/
01
b1110 0
0-
b1000011100 ,
b10010 +
b11 *
b110110 )
b100100 (
b10010 2
1.
#185
0'
#190
b1000111010 %
b11111 &
1'
1/
11
b11101 0
1-
b1000111010 ,
b10011 +
b100 *
b111001 )
b100110 (
b10011 2
1.
#195
0'
#200
1'
b10100 2
0.
#205
0'
#210
1"
b11101 #
1'
#215
0'
#220
b0 #
1'
